LCONST_0
LSTORE 1
INVOKESTATIC java/lang/System.nanoTime ()J
LSTORE 3
INVOKESTATIC java/lang/System.nanoTime ()J
LLOAD 3
LSUB
LSTORE 1
INVOKESTATIC org/openjdk/btrace/runtime/LinkingFlag.get ()I
IFNE L2
LLOAD 1
INVOKESTATIC resources/DerivedClass.$btrace$org$openjdk$btrace$runtime$auxiliary$BTRACE53$onInit (J)V
L2
FRAME FULL [resources/DerivedClass J J] []
L3
LOCALVARIABLE this Lresources/DerivedClass; L0 L3 0
MAXSTACK = 4
MAXLOCALS = 5

// access flags 0xA
private static $btrace$org$openjdk$btrace$runtime$auxiliary$BTRACE53$onInit(J)V
@Lorg/openjdk/btrace/core/annotations/OnMethod;(clazz="/.*\\.DerivedClass/", method="<init>", location=@Lorg/openjdk/btrace/core/annotations/Location;(value=Lorg/openjdk/btrace/core/annotations/Kind;.RETURN))
// annotable parameter count: 1 (visible)
@Lorg/openjdk/btrace/core/annotations/Duration;() // parameter 0
TRYCATCHBLOCK L0 L1 L1 java/lang/Throwable
GETSTATIC org/openjdk/btrace/runtime/auxiliary/BTRACE53.runtime : Lorg/openjdk/btrace/runtime/BTraceRuntimeImplBase;
INVOKESTATIC org/openjdk/btrace/runtime/BTraceRuntimeAccess.enter (Lorg/openjdk/btrace/core/BTraceRuntime$Impl;)Z
IFNE L0
RETURN
L0
FRAME SAME
LDC "init: "
LLOAD 0
INVOKESTATIC org/openjdk/btrace/core/BTraceUtils.str (J)Ljava/lang/String;
INVOKESTATIC org/openjdk/btrace/core/BTraceUtils.strcat (Ljava/lang/String;Ljava/lang/String;)Ljava/lang/String;
INVOKESTATIC org/openjdk/btrace/core/BTraceUtils.println (Ljava/lang/Object;)V
GETSTATIC org/openjdk/btrace/runtime/auxiliary/BTRACE53.runtime : Lorg/openjdk/btrace/runtime/BTraceRuntimeImplBase;
INVOKEVIRTUAL org/openjdk/btrace/runtime/BTraceRuntimeImplBase.leave ()V
RETURN
L1
FRAME SAME1 java/lang/Throwable
GETSTATIC org/openjdk/btrace/runtime/auxiliary/BTRACE53.runtime : Lorg/openjdk/btrace/runtime/BTraceRuntimeImplBase;
DUP_X1
SWAP
INVOKEVIRTUAL org/openjdk/btrace/runtime/BTraceRuntimeImplBase.handleException (Ljava/lang/Throwable;)V
GETSTATIC org/openjdk/btrace/runtime/auxiliary/BTRACE53.runtime : Lorg/openjdk/btrace/runtime/BTraceRuntimeImplBase;
INVOKEVIRTUAL org/openjdk/btrace/runtime/BTraceRuntimeImplBase.leave ()V
RETURN
MAXSTACK = 3
MAXLOCALS = 2