INVOKESTATIC org/openjdk/btrace/runtime/LinkingFlag.get ()I
IFNE L0
ALOAD 0
ALOAD 1
ALOAD 2
INVOKESTATIC resources/InterestingVarsClass.$btrace$org$openjdk$btrace$runtime$auxiliary$InterestingVarsTest$entry (Ljava/lang/String;Ljava/lang/String;Ljava/lang/String;)V
FRAME SAME

// access flags 0xA
private static $btrace$org$openjdk$btrace$runtime$auxiliary$InterestingVarsTest$entry(Ljava/lang/String;Ljava/lang/String;Ljava/lang/String;)V
@Lorg/openjdk/btrace/core/annotations/OnMethod;(clazz="/.*\\.InterestingVarsClass/", method="initAndStartApp")
TRYCATCHBLOCK L0 L1 L1 java/lang/Throwable
GETSTATIC org/openjdk/btrace/runtime/auxiliary/InterestingVarsTest.runtime : Lorg/openjdk/btrace/runtime/BTraceRuntimeImplBase;
INVOKESTATIC org/openjdk/btrace/runtime/BTraceRuntimeAccess.enter (Lorg/openjdk/btrace/core/BTraceRuntime$Impl;)Z
IFNE L0
RETURN
L0
FRAME SAME
ALOAD 0
INVOKESTATIC org/openjdk/btrace/core/BTraceUtils.println (Ljava/lang/Object;)V
GETSTATIC org/openjdk/btrace/runtime/auxiliary/InterestingVarsTest.runtime : Lorg/openjdk/btrace/runtime/BTraceRuntimeImplBase;
INVOKEVIRTUAL org/openjdk/btrace/runtime/BTraceRuntimeImplBase.leave ()V
RETURN
L1
FRAME SAME1 java/lang/Throwable
GETSTATIC org/openjdk/btrace/runtime/auxiliary/InterestingVarsTest.runtime : Lorg/openjdk/btrace/runtime/BTraceRuntimeImplBase;
DUP_X1
SWAP
INVOKEVIRTUAL org/openjdk/btrace/runtime/BTraceRuntimeImplBase.handleException (Ljava/lang/Throwable;)V
GETSTATIC org/openjdk/btrace/runtime/auxiliary/InterestingVarsTest.runtime : Lorg/openjdk/btrace/runtime/BTraceRuntimeImplBase;
INVOKEVIRTUAL org/openjdk/btrace/runtime/BTraceRuntimeImplBase.leave ()V
RETURN
MAXSTACK = 3
MAXLOCALS = 3