ICONST_0
ISTORE 6
GETSTATIC org/openjdk/btrace/runtime/auxiliary/ArgsSampledNoSampling.$btrace$$level : I
DUP
ISTORE 7
IFLE L0
ICONST_1
INVOKESTATIC org/openjdk/btrace/instr/MethodTracker.hit (I)Z
ISTORE 6
FRAME APPEND [I I]
ILOAD 7
IFLE L1
ILOAD 6
IFEQ L2
L1
FRAME SAME
GETSTATIC org/openjdk/btrace/runtime/auxiliary/ArgsSampledNoSampling.$btrace$$level : I
ICONST_1
IF_ICMPLT L2
INVOKESTATIC org/openjdk/btrace/runtime/LinkingFlag.get ()I
IFNE L2
ALOAD 0
ALOAD 1
LLOAD 2
ALOAD 4
ALOAD 5
INVOKEDYNAMIC $btrace$org$openjdk$btrace$runtime$auxiliary$ArgsSampledNoSampling$argsSampled(Ljava/lang/Object;Ljava/lang/String;J[Ljava/lang/String;[I)V [
// handle kind 0x6 : INVOKESTATIC
org/openjdk/btrace/runtime/Indy.bootstrap(Ljava/lang/invoke/MethodHandles$Lookup;Ljava/lang/String;Ljava/lang/invoke/MethodType;Ljava/lang/String;)Ljava/lang/invoke/CallSite;
// arguments:
"org/openjdk/btrace/runtime/auxiliary/ArgsSampledNoSampling"
]
L2
FRAME SAME
GETSTATIC org/openjdk/btrace/runtime/auxiliary/ArgsSampledNoSampling.$btrace$$level : I
ICONST_1
IF_ICMPLT L3
INVOKESTATIC org/openjdk/btrace/runtime/LinkingFlag.get ()I
IFNE L3
ALOAD 0
ALOAD 1
LLOAD 2
ALOAD 4
ALOAD 5
INVOKEDYNAMIC $btrace$org$openjdk$btrace$runtime$auxiliary$ArgsSampledNoSampling$argsNoSampling(Ljava/lang/Object;Ljava/lang/String;J[Ljava/lang/String;[I)V [
// handle kind 0x6 : INVOKESTATIC
org/openjdk/btrace/runtime/Indy.bootstrap(Ljava/lang/invoke/MethodHandles$Lookup;Ljava/lang/String;Ljava/lang/invoke/MethodType;Ljava/lang/String;)Ljava/lang/invoke/CallSite;
// arguments:
"org/openjdk/btrace/runtime/auxiliary/ArgsSampledNoSampling"
]
L3
LINENUMBER 57 L3
FRAME SAME
L4
LOCALVARIABLE this Lresources/OnMethodTest; L3 L4 0
LOCALVARIABLE a Ljava/lang/String; L3 L4 1
LOCALVARIABLE b J L3 L4 2
LOCALVARIABLE c [Ljava/lang/String; L3 L4 4
LOCALVARIABLE d [I L3 L4 5
MAXSTACK = 6
MAXLOCALS = 8