LSTORE 4
ASTORE 6
ASTORE 7
ICONST_0
ISTORE 8
GETSTATIC org/openjdk/btrace/runtime/auxiliary/MethodCallSampledAdaptive.$btrace$$level : I
DUP
ISTORE 9
IFLE L1
ICONST_2
INVOKESTATIC org/openjdk/btrace/instr/MethodTracker.hitAdaptive (I)Z
ISTORE 8
L1
FRAME FULL [resources/OnMethodTest java/lang/String J J java/lang/String resources/OnMethodTest I I] []
ILOAD 9
IFLE L2
ILOAD 8
IFEQ L3
L2
FRAME SAME
GETSTATIC org/openjdk/btrace/runtime/auxiliary/MethodCallSampledAdaptive.$btrace$$level : I
ICONST_1
IF_ICMPLT L3
INVOKESTATIC org/openjdk/btrace/runtime/LinkingFlag.get ()I
IFNE L3
ALOAD 0
ALOAD 6
LLOAD 4
ALOAD 7
LDC "special long resources.OnMethodTest#callTarget(java.lang.String, long)"
LDC "resources.OnMethodTest"
LDC "callTopLevel"
INVOKEDYNAMIC $btrace$org$openjdk$btrace$runtime$auxiliary$MethodCallSampledAdaptive$args(Ljava/lang/Object;Ljava/lang/String;JLjava/lang/Object;Ljava/lang/String;Ljava/lang/String;Ljava/lang/String;)V [
// handle kind 0x6 : INVOKESTATIC
org/openjdk/btrace/runtime/Indy.bootstrap(Ljava/lang/invoke/MethodHandles$Lookup;Ljava/lang/String;Ljava/lang/invoke/MethodType;Ljava/lang/String;)Ljava/lang/invoke/CallSite;
// arguments:
"org/openjdk/btrace/runtime/auxiliary/MethodCallSampledAdaptive"
]
L3
FRAME SAME
ALOAD 7
ALOAD 6
LLOAD 4
ILOAD 8
IFEQ L4
ICONST_2
INVOKESTATIC org/openjdk/btrace/instr/MethodTracker.updateEndTs (I)V
L4
FRAME SAME1 J
L5
LOCALVARIABLE this Lresources/OnMethodTest; L0 L5 0
LOCALVARIABLE a Ljava/lang/String; L0 L5 1
LOCALVARIABLE b J L0 L5 2
MAXSTACK = 8
MAXLOCALS = 10