INVOKESTATIC org/openjdk/btrace/runtime/LinkingFlag.get ()I
IFNE L0
ALOAD 0
ALOAD 1
INVOKESTATIC resources/OnMethodTest.$btrace$org$openjdk$btrace$runtime$auxiliary$ArgsSigMatch$m3 (Ljava/lang/Object;Ljava/util/ArrayList;)V
FRAME SAME
INVOKESTATIC org/openjdk/btrace/runtime/LinkingFlag.get ()I
IFNE L1
ALOAD 0
ALOAD 1
INVOKESTATIC resources/OnMethodTest.$btrace$org$openjdk$btrace$runtime$auxiliary$ArgsSigMatch$m1 (Ljava/lang/Object;Ljava/util/List;)V
L1
LINENUMBER 173 L1
FRAME SAME
L2
LOCALVARIABLE this Lresources/OnMethodTest; L1 L2 0
LOCALVARIABLE l Ljava/util/ArrayList; L1 L2 1
MAXSTACK = 2

// access flags 0xA
// signature (Ljava/lang/Object;Ljava/util/List<Ljava/lang/String;>;)V
// declaration: void $btrace$org$openjdk$btrace$runtime$auxiliary$ArgsSigMatch$m1(java.lang.Object, java.util.List<java.lang.String>)
private static $btrace$org$openjdk$btrace$runtime$auxiliary$ArgsSigMatch$m1(Ljava/lang/Object;Ljava/util/List;)V
@Lorg/openjdk/btrace/core/annotations/OnMethod;(clazz="/.*\\.OnMethodTest/", method="argsTypeMatch")
// annotable parameter count: 2 (visible)
@Lorg/openjdk/btrace/core/annotations/Self;() // parameter 0
TRYCATCHBLOCK L0 L1 L1 java/lang/Throwable
GETSTATIC org/openjdk/btrace/runtime/auxiliary/ArgsSigMatch.runtime : Lorg/openjdk/btrace/runtime/BTraceRuntimeImplBase;
INVOKESTATIC org/openjdk/btrace/runtime/BTraceRuntimeAccess.enter (Lorg/openjdk/btrace/core/BTraceRuntime$Impl;)Z
IFNE L0
RETURN
L0
FRAME SAME
LDC "m1"
INVOKESTATIC org/openjdk/btrace/core/BTraceUtils.println (Ljava/lang/Object;)V
GETSTATIC org/openjdk/btrace/runtime/auxiliary/ArgsSigMatch.runtime : Lorg/openjdk/btrace/runtime/BTraceRuntimeImplBase;
INVOKEVIRTUAL org/openjdk/btrace/runtime/BTraceRuntimeImplBase.leave ()V
RETURN
L1
FRAME SAME1 java/lang/Throwable
GETSTATIC org/openjdk/btrace/runtime/auxiliary/ArgsSigMatch.runtime : Lorg/openjdk/btrace/runtime/BTraceRuntimeImplBase;
DUP_X1
SWAP
INVOKEVIRTUAL org/openjdk/btrace/runtime/BTraceRuntimeImplBase.handleException (Ljava/lang/Throwable;)V
GETSTATIC org/openjdk/btrace/runtime/auxiliary/ArgsSigMatch.runtime : Lorg/openjdk/btrace/runtime/BTraceRuntimeImplBase;
INVOKEVIRTUAL org/openjdk/btrace/runtime/BTraceRuntimeImplBase.leave ()V
RETURN
MAXSTACK = 3
MAXLOCALS = 2

// access flags 0xA
// signature (Ljava/lang/Object;Ljava/util/ArrayList<Ljava/lang/String;>;)V
// declaration: void $btrace$org$openjdk$btrace$runtime$auxiliary$ArgsSigMatch$m3(java.lang.Object, java.util.ArrayList<java.lang.String>)
private static $btrace$org$openjdk$btrace$runtime$auxiliary$ArgsSigMatch$m3(Ljava/lang/Object;Ljava/util/ArrayList;)V
@Lorg/openjdk/btrace/core/annotations/OnMethod;(clazz="/.*\\.OnMethodTest/", method="argsTypeMatch", exactTypeMatch=true)
// annotable parameter count: 2 (visible)
@Lorg/openjdk/btrace/core/annotations/Self;() // parameter 0
TRYCATCHBLOCK L0 L1 L1 java/lang/Throwable
GETSTATIC org/openjdk/btrace/runtime/auxiliary/ArgsSigMatch.runtime : Lorg/openjdk/btrace/runtime/BTraceRuntimeImplBase;
INVOKESTATIC org/openjdk/btrace/runtime/BTraceRuntimeAccess.enter (Lorg/openjdk/btrace/core/BTraceRuntime$Impl;)Z
IFNE L0
RETURN
L0
FRAME SAME
LDC "m3"
INVOKESTATIC org/openjdk/btrace/core/BTraceUtils.println (Ljava/lang/Object;)V
GETSTATIC org/openjdk/btrace/runtime/auxiliary/ArgsSigMatch.runtime : Lorg/openjdk/btrace/runtime/BTraceRuntimeImplBase;
INVOKEVIRTUAL org/openjdk/btrace/runtime/BTraceRuntimeImplBase.leave ()V
RETURN
L1
FRAME SAME1 java/lang/Throwable
GETSTATIC org/openjdk/btrace/runtime/auxiliary/ArgsSigMatch.runtime : Lorg/openjdk/btrace/runtime/BTraceRuntimeImplBase;
DUP_X1
SWAP
INVOKEVIRTUAL org/openjdk/btrace/runtime/BTraceRuntimeImplBase.handleException (Ljava/lang/Throwable;)V
GETSTATIC org/openjdk/btrace/runtime/auxiliary/ArgsSigMatch.runtime : Lorg/openjdk/btrace/runtime/BTraceRuntimeImplBase;
INVOKEVIRTUAL org/openjdk/btrace/runtime/BTraceRuntimeImplBase.leave ()V
RETURN
MAXSTACK = 3
MAXLOCALS = 2