LSTORE 1
LLOAD 1
INVOKESTATIC org/openjdk/btrace/runtime/LinkingFlag.get ()I
IFNE L1
ALOAD 0
ACONST_NULL
LDC "sField"
LLOAD 1
INVOKESTATIC resources/OnMethodTest.$btrace$org$openjdk$btrace$runtime$auxiliary$FieldSetAfterStatic$args (Ljava/lang/Object;Ljava/lang/Object;Ljava/lang/String;J)V
FRAME APPEND [J]
MAXSTACK = 5
MAXLOCALS = 3

// access flags 0xA
private static $btrace$org$openjdk$btrace$runtime$auxiliary$FieldSetAfterStatic$args(Ljava/lang/Object;Ljava/lang/Object;Ljava/lang/String;J)V
@Lorg/openjdk/btrace/core/annotations/OnMethod;(clazz="/.*\\.OnMethodTest/", method="staticField", location=@Lorg/openjdk/btrace/core/annotations/Location;(value=Lorg/openjdk/btrace/core/annotations/Kind;.FIELD_SET, clazz="resources.OnMethodTest", field="/^sField$/", where=Lorg/openjdk/btrace/core/annotations/Where;.AFTER))
// annotable parameter count: 4 (visible)
@Lorg/openjdk/btrace/core/annotations/Self;() // parameter 0
@Lorg/openjdk/btrace/core/annotations/TargetInstance;() // parameter 1
@Lorg/openjdk/btrace/core/annotations/TargetMethodOrField;() // parameter 2
TRYCATCHBLOCK L0 L1 L1 java/lang/Throwable
GETSTATIC org/openjdk/btrace/runtime/auxiliary/FieldSetAfterStatic.runtime : Lorg/openjdk/btrace/runtime/BTraceRuntimeImplBase;
INVOKESTATIC org/openjdk/btrace/runtime/BTraceRuntimeAccess.enter (Lorg/openjdk/btrace/core/BTraceRuntime$Impl;)Z
IFNE L0
RETURN
L0
FRAME SAME
LDC "args"
INVOKESTATIC org/openjdk/btrace/core/BTraceUtils.println (Ljava/lang/Object;)V
GETSTATIC org/openjdk/btrace/runtime/auxiliary/FieldSetAfterStatic.runtime : Lorg/openjdk/btrace/runtime/BTraceRuntimeImplBase;
INVOKEVIRTUAL org/openjdk/btrace/runtime/BTraceRuntimeImplBase.leave ()V
RETURN
L1
FRAME SAME1 java/lang/Throwable
GETSTATIC org/openjdk/btrace/runtime/auxiliary/FieldSetAfterStatic.runtime : Lorg/openjdk/btrace/runtime/BTraceRuntimeImplBase;
DUP_X1
SWAP
INVOKEVIRTUAL org/openjdk/btrace/runtime/BTraceRuntimeImplBase.handleException (Ljava/lang/Throwable;)V
GETSTATIC org/openjdk/btrace/runtime/auxiliary/FieldSetAfterStatic.runtime : Lorg/openjdk/btrace/runtime/BTraceRuntimeImplBase;
INVOKEVIRTUAL org/openjdk/btrace/runtime/BTraceRuntimeImplBase.leave ()V
RETURN
MAXSTACK = 3
MAXLOCALS = 5