ICONST_0
ISTORE 6
GETSTATIC org/openjdk/btrace/runtime/auxiliary/ArgsSampledNoSampling.$btrace$$level : I
DUP
ISTORE 7
IFLE L0
ICONST_1
INVOKESTATIC org/openjdk/btrace/instr/MethodTracker.hit (I)Z
ISTORE 6
FRAME APPEND [I I]
ILOAD 7
IFLE L1
ILOAD 6
IFEQ L2
L1
FRAME SAME
GETSTATIC org/openjdk/btrace/runtime/auxiliary/ArgsSampledNoSampling.$btrace$$level : I
ICONST_1
IF_ICMPLT L2
INVOKESTATIC org/openjdk/btrace/runtime/LinkingFlag.get ()I
IFNE L2
ALOAD 0
ALOAD 1
LLOAD 2
ALOAD 4
ALOAD 5
INVOKESTATIC resources/OnMethodTest.$btrace$org$openjdk$btrace$runtime$auxiliary$ArgsSampledNoSampling$argsSampled (Ljava/lang/Object;Ljava/lang/String;J[Ljava/lang/String;[I)V
L2
FRAME SAME
GETSTATIC org/openjdk/btrace/runtime/auxiliary/ArgsSampledNoSampling.$btrace$$level : I
ICONST_1
IF_ICMPLT L3
INVOKESTATIC org/openjdk/btrace/runtime/LinkingFlag.get ()I
IFNE L3
ALOAD 0
ALOAD 1
LLOAD 2
ALOAD 4
ALOAD 5
INVOKESTATIC resources/OnMethodTest.$btrace$org$openjdk$btrace$runtime$auxiliary$ArgsSampledNoSampling$argsNoSampling (Ljava/lang/Object;Ljava/lang/String;J[Ljava/lang/String;[I)V
L3
LINENUMBER 57 L3
FRAME SAME
L4
LOCALVARIABLE this Lresources/OnMethodTest; L3 L4 0
LOCALVARIABLE a Ljava/lang/String; L3 L4 1
LOCALVARIABLE b J L3 L4 2
LOCALVARIABLE c [Ljava/lang/String; L3 L4 4
LOCALVARIABLE d [I L3 L4 5
MAXSTACK = 6
MAXLOCALS = 8

// access flags 0xA
private static $btrace$org$openjdk$btrace$runtime$auxiliary$ArgsSampledNoSampling$argsNoSampling(Ljava/lang/Object;Ljava/lang/String;J[Ljava/lang/String;[I)V
@Lorg/openjdk/btrace/core/annotations/OnMethod;(clazz="/.*\\.OnMethodTest/", method="args", enableAt=@Lorg/openjdk/btrace/core/annotations/Level;(value=">=1"))
// annotable parameter count: 5 (visible)
@Lorg/openjdk/btrace/core/annotations/Self;() // parameter 0
TRYCATCHBLOCK L0 L1 L1 java/lang/Throwable
GETSTATIC org/openjdk/btrace/runtime/auxiliary/ArgsSampledNoSampling.runtime : Lorg/openjdk/btrace/runtime/BTraceRuntimeImplBase;
INVOKESTATIC org/openjdk/btrace/runtime/BTraceRuntimeAccess.enter (Lorg/openjdk/btrace/core/BTraceRuntime$Impl;)Z
IFNE L0
RETURN
L0
FRAME SAME
NEW java/lang/StringBuilder
DUP
INVOKESPECIAL java/lang/StringBuilder.<init> ()V
LDC "this = "
INVOKEVIRTUAL java/lang/StringBuilder.append (Ljava/lang/String;)Ljava/lang/StringBuilder;
ALOAD 0
INVOKEVIRTUAL java/lang/StringBuilder.append (Ljava/lang/Object;)Ljava/lang/StringBuilder;
INVOKEVIRTUAL java/lang/StringBuilder.toString ()Ljava/lang/String;
INVOKESTATIC org/openjdk/btrace/core/BTraceUtils.println (Ljava/lang/Object;)V
LDC "args"
INVOKESTATIC org/openjdk/btrace/core/BTraceUtils.println (Ljava/lang/Object;)V
GETSTATIC org/openjdk/btrace/runtime/auxiliary/ArgsSampledNoSampling.runtime : Lorg/openjdk/btrace/runtime/BTraceRuntimeImplBase;
INVOKEVIRTUAL org/openjdk/btrace/runtime/BTraceRuntimeImplBase.leave ()V
RETURN
L1
FRAME SAME1 java/lang/Throwable
GETSTATIC org/openjdk/btrace/runtime/auxiliary/ArgsSampledNoSampling.runtime : Lorg/openjdk/btrace/runtime/BTraceRuntimeImplBase;
DUP_X1
SWAP
INVOKEVIRTUAL org/openjdk/btrace/runtime/BTraceRuntimeImplBase.handleException (Ljava/lang/Throwable;)V
GETSTATIC org/openjdk/btrace/runtime/auxiliary/ArgsSampledNoSampling.runtime : Lorg/openjdk/btrace/runtime/BTraceRuntimeImplBase;
INVOKEVIRTUAL org/openjdk/btrace/runtime/BTraceRuntimeImplBase.leave ()V
RETURN
MAXSTACK = 3
MAXLOCALS = 6

// access flags 0xA
private static $btrace$org$openjdk$btrace$runtime$auxiliary$ArgsSampledNoSampling$argsSampled(Ljava/lang/Object;Ljava/lang/String;J[Ljava/lang/String;[I)V
@Lorg/openjdk/btrace/core/annotations/OnMethod;(clazz="/.*\\.OnMethodTest/", method="args", enableAt=@Lorg/openjdk/btrace/core/annotations/Level;(value=">=1"))
@Lorg/openjdk/btrace/core/annotations/Sampled;(kind=Lorg/openjdk/btrace/core/annotations/Sampled$Sampler;.Const) // invisible
// annotable parameter count: 5 (visible)
@Lorg/openjdk/btrace/core/annotations/Self;() // parameter 0
TRYCATCHBLOCK L0 L1 L1 java/lang/Throwable
GETSTATIC org/openjdk/btrace/runtime/auxiliary/ArgsSampledNoSampling.runtime : Lorg/openjdk/btrace/runtime/BTraceRuntimeImplBase;
INVOKESTATIC org/openjdk/btrace/runtime/BTraceRuntimeAccess.enter (Lorg/openjdk/btrace/core/BTraceRuntime$Impl;)Z
IFNE L0
RETURN
L0
FRAME SAME
NEW java/lang/StringBuilder
DUP
INVOKESPECIAL java/lang/StringBuilder.<init> ()V
LDC "this = "
INVOKEVIRTUAL java/lang/StringBuilder.append (Ljava/lang/String;)Ljava/lang/StringBuilder;
ALOAD 0
INVOKEVIRTUAL java/lang/StringBuilder.append (Ljava/lang/Object;)Ljava/lang/StringBuilder;
INVOKEVIRTUAL java/lang/StringBuilder.toString ()Ljava/lang/String;
INVOKESTATIC org/openjdk/btrace/core/BTraceUtils.println (Ljava/lang/Object;)V
LDC "args"
INVOKESTATIC org/openjdk/btrace/core/BTraceUtils.println (Ljava/lang/Object;)V
GETSTATIC org/openjdk/btrace/runtime/auxiliary/ArgsSampledNoSampling.runtime : Lorg/openjdk/btrace/runtime/BTraceRuntimeImplBase;
INVOKEVIRTUAL org/openjdk/btrace/runtime/BTraceRuntimeImplBase.leave ()V
RETURN
L1
FRAME SAME1 java/lang/Throwable
GETSTATIC org/openjdk/btrace/runtime/auxiliary/ArgsSampledNoSampling.runtime : Lorg/openjdk/btrace/runtime/BTraceRuntimeImplBase;
DUP_X1
SWAP
INVOKEVIRTUAL org/openjdk/btrace/runtime/BTraceRuntimeImplBase.handleException (Ljava/lang/Throwable;)V
GETSTATIC org/openjdk/btrace/runtime/auxiliary/ArgsSampledNoSampling.runtime : Lorg/openjdk/btrace/runtime/BTraceRuntimeImplBase;
INVOKEVIRTUAL org/openjdk/btrace/runtime/BTraceRuntimeImplBase.leave ()V
RETURN
MAXSTACK = 3
MAXLOCALS = 6