LSTORE 4
ASTORE 6
ASTORE 7
ALOAD 7
ALOAD 6
LLOAD 4
GETSTATIC org/openjdk/btrace/runtime/auxiliary/MethodCallReturnAugmented1.$btrace$$level : I
ICONST_1
IF_ICMPLT L1
INVOKESTATIC org/openjdk/btrace/runtime/LinkingFlag.get ()I
IFNE L1
LSTORE 8
LLOAD 8
ALOAD 6
LLOAD 4
INVOKESTATIC resources/OnMethodTest.$btrace$org$openjdk$btrace$runtime$auxiliary$MethodCallReturnAugmented1$args (JLjava/lang/String;J)J
L1
FRAME FULL [resources/OnMethodTest java/lang/String J J java/lang/String resources/OnMethodTest] [J]
L2
LOCALVARIABLE this Lresources/OnMethodTest; L0 L2 0
LOCALVARIABLE a Ljava/lang/String; L0 L2 1
LOCALVARIABLE b J L0 L2 2
MAXLOCALS = 10

// access flags 0xA
private static $btrace$org$openjdk$btrace$runtime$auxiliary$MethodCallReturnAugmented1$args(JLjava/lang/String;J)J
@Lorg/openjdk/btrace/core/annotations/OnMethod;(clazz="/.*\\.OnMethodTest/", method="callTopLevel", location=@Lorg/openjdk/btrace/core/annotations/Location;(value=Lorg/openjdk/btrace/core/annotations/Kind;.CALL, clazz="/.*\\.OnMethodTest/", method="callTarget", where=Lorg/openjdk/btrace/core/annotations/Where;.AFTER), enableAt=@Lorg/openjdk/btrace/core/annotations/Level;(value=">=1"))
// annotable parameter count: 3 (visible)
@Lorg/openjdk/btrace/core/annotations/Return;() // parameter 0
TRYCATCHBLOCK L0 L1 L1 java/lang/Throwable
GETSTATIC org/openjdk/btrace/runtime/auxiliary/MethodCallReturnAugmented1.runtime : Lorg/openjdk/btrace/runtime/BTraceRuntimeImplBase;
INVOKESTATIC org/openjdk/btrace/runtime/BTraceRuntimeAccess.enter (Lorg/openjdk/btrace/core/BTraceRuntime$Impl;)Z
IFNE L0
LLOAD 0
LRETURN
L0
FRAME SAME
LDC "args"
INVOKESTATIC org/openjdk/btrace/core/BTraceUtils.println (Ljava/lang/Object;)V
LLOAD 0
LCONST_1
LADD
GETSTATIC org/openjdk/btrace/runtime/auxiliary/MethodCallReturnAugmented1.runtime : Lorg/openjdk/btrace/runtime/BTraceRuntimeImplBase;
INVOKEVIRTUAL org/openjdk/btrace/runtime/BTraceRuntimeImplBase.leave ()V
LRETURN
L1
FRAME SAME1 java/lang/Throwable
GETSTATIC org/openjdk/btrace/runtime/auxiliary/MethodCallReturnAugmented1.runtime : Lorg/openjdk/btrace/runtime/BTraceRuntimeImplBase;
DUP_X1
SWAP
INVOKEVIRTUAL org/openjdk/btrace/runtime/BTraceRuntimeImplBase.handleException (Ljava/lang/Throwable;)V
LLOAD 0
GETSTATIC org/openjdk/btrace/runtime/auxiliary/MethodCallReturnAugmented1.runtime : Lorg/openjdk/btrace/runtime/BTraceRuntimeImplBase;
INVOKEVIRTUAL org/openjdk/btrace/runtime/BTraceRuntimeImplBase.leave ()V
LRETURN
MAXSTACK = 4
MAXLOCALS = 5