INVOKESTATIC org/openjdk/btrace/runtime/LinkingFlag.get ()I
IFNE L0
ALOAD 0
LDC "aMethod"
INVOKEDYNAMIC $btrace$org$openjdk$btrace$runtime$auxiliary$BTRACE106$o1(Ljava/lang/Object;Ljava/lang/String;)V [
// handle kind 0x6 : INVOKESTATIC
org/openjdk/btrace/runtime/Indy.bootstrap(Ljava/lang/invoke/MethodHandles$Lookup;Ljava/lang/String;Ljava/lang/invoke/MethodType;Ljava/lang/String;)Ljava/lang/invoke/CallSite;
// arguments:
"org/openjdk/btrace/runtime/auxiliary/BTRACE106"
]
FRAME SAME
LCONST_0
LSTORE 1
INVOKESTATIC java/lang/System.nanoTime ()J
LSTORE 3
INVOKESTATIC java/lang/System.nanoTime ()J
LLOAD 3
LSUB
LSTORE 1
INVOKESTATIC org/openjdk/btrace/runtime/LinkingFlag.get ()I
IFNE L2
ALOAD 0
LDC "bMethod"
LLOAD 1
INVOKEDYNAMIC $btrace$org$openjdk$btrace$runtime$auxiliary$BTRACE106$o3(Ljava/lang/Object;Ljava/lang/String;J)V [
// handle kind 0x6 : INVOKESTATIC
org/openjdk/btrace/runtime/Indy.bootstrap(Ljava/lang/invoke/MethodHandles$Lookup;Ljava/lang/String;Ljava/lang/invoke/MethodType;Ljava/lang/String;)Ljava/lang/invoke/CallSite;
// arguments:
"org/openjdk/btrace/runtime/auxiliary/BTRACE106"
]
L2
FRAME APPEND [J J]
INVOKESTATIC org/openjdk/btrace/runtime/LinkingFlag.get ()I
IFNE L3
ALOAD 0
LDC "bMethod"
LLOAD 1
INVOKEDYNAMIC $btrace$org$openjdk$btrace$runtime$auxiliary$BTRACE106$o2(Ljava/lang/Object;Ljava/lang/String;J)V [
// handle kind 0x6 : INVOKESTATIC
org/openjdk/btrace/runtime/Indy.bootstrap(Ljava/lang/invoke/MethodHandles$Lookup;Ljava/lang/String;Ljava/lang/invoke/MethodType;Ljava/lang/String;)Ljava/lang/invoke/CallSite;
// arguments:
"org/openjdk/btrace/runtime/auxiliary/BTRACE106"
]
L3
FRAME SAME
L4
LOCALVARIABLE this Lresources/issues/BTRACE106; L0 L4 0
MAXSTACK = 4
MAXLOCALS = 5