INVOKESTATIC org/openjdk/btrace/runtime/LinkingFlag.get ()I
IFNE L0
INVOKEDYNAMIC $btrace$org$openjdk$btrace$runtime$auxiliary$ServicesTest$testSimpleService()V [
// handle kind 0x6 : INVOKESTATIC
org/openjdk/btrace/runtime/Indy.bootstrap(Ljava/lang/invoke/MethodHandles$Lookup;Ljava/lang/String;Ljava/lang/invoke/MethodType;Ljava/lang/String;)Ljava/lang/invoke/CallSite;
// arguments:
"org/openjdk/btrace/runtime/auxiliary/ServicesTest"
]
FRAME SAME
MAXSTACK = 1
INVOKESTATIC org/openjdk/btrace/runtime/LinkingFlag.get ()I
IFNE L0
LDC "resources.OnMethodTest"
INVOKEDYNAMIC $btrace$org$openjdk$btrace$runtime$auxiliary$ServicesTest$testFieldInjection(Ljava/lang/String;)V [
// handle kind 0x6 : INVOKESTATIC
org/openjdk/btrace/runtime/Indy.bootstrap(Ljava/lang/invoke/MethodHandles$Lookup;Ljava/lang/String;Ljava/lang/invoke/MethodType;Ljava/lang/String;)Ljava/lang/invoke/CallSite;
// arguments:
"org/openjdk/btrace/runtime/auxiliary/ServicesTest"
]
FRAME SAME
MAXSTACK = 1
INVOKESTATIC org/openjdk/btrace/runtime/LinkingFlag.get ()I
IFNE L0
ALOAD 1
LLOAD 2
ALOAD 4
ALOAD 5
INVOKEDYNAMIC $btrace$org$openjdk$btrace$runtime$auxiliary$ServicesTest$testRuntimeService(Ljava/lang/String;J[Ljava/lang/String;[I)V [
// handle kind 0x6 : INVOKESTATIC
org/openjdk/btrace/runtime/Indy.bootstrap(Ljava/lang/invoke/MethodHandles$Lookup;Ljava/lang/String;Ljava/lang/invoke/MethodType;Ljava/lang/String;)Ljava/lang/invoke/CallSite;
// arguments:
"org/openjdk/btrace/runtime/auxiliary/ServicesTest"
]
FRAME SAME
MAXSTACK = 5
INVOKESTATIC org/openjdk/btrace/runtime/LinkingFlag.get ()I
IFNE L0
ALOAD 0
LLOAD 1
ALOAD 3
ALOAD 4
INVOKEDYNAMIC $btrace$org$openjdk$btrace$runtime$auxiliary$ServicesTest$testSingletonService(Ljava/lang/String;J[Ljava/lang/String;[I)V [
// handle kind 0x6 : INVOKESTATIC
org/openjdk/btrace/runtime/Indy.bootstrap(Ljava/lang/invoke/MethodHandles$Lookup;Ljava/lang/String;Ljava/lang/invoke/MethodType;Ljava/lang/String;)Ljava/lang/invoke/CallSite;
// arguments:
"org/openjdk/btrace/runtime/auxiliary/ServicesTest"
]
FRAME SAME
MAXSTACK = 5