INVOKESTATIC org/openjdk/btrace/runtime/LinkingFlag.get ()I
IFNE L1
LDC "public void resources.OnMethodTest#<init>"
INVOKEDYNAMIC $btrace$org$openjdk$btrace$runtime$auxiliary$TraceAllTest$doall(Ljava/lang/String;)V [
// handle kind 0x6 : INVOKESTATIC
org/openjdk/btrace/runtime/Indy.bootstrap(Ljava/lang/invoke/MethodHandles$Lookup;Ljava/lang/String;Ljava/lang/invoke/MethodType;Ljava/lang/String;)Ljava/lang/invoke/CallSite;
// arguments:
"org/openjdk/btrace/runtime/auxiliary/TraceAllTest"
]
FRAME FULL [resources/OnMethodTest] []
INVOKESTATIC org/openjdk/btrace/runtime/LinkingFlag.get ()I
IFNE L1
LDC "private void resources.OnMethodTest#<init>(java.lang.String)"
INVOKEDYNAMIC $btrace$org$openjdk$btrace$runtime$auxiliary$TraceAllTest$doall(Ljava/lang/String;)V [
// handle kind 0x6 : INVOKESTATIC
org/openjdk/btrace/runtime/Indy.bootstrap(Ljava/lang/invoke/MethodHandles$Lookup;Ljava/lang/String;Ljava/lang/invoke/MethodType;Ljava/lang/String;)Ljava/lang/invoke/CallSite;
// arguments:
"org/openjdk/btrace/runtime/auxiliary/TraceAllTest"
]
FRAME FULL [resources/OnMethodTest java/lang/String] []
INVOKESTATIC org/openjdk/btrace/runtime/LinkingFlag.get ()I
IFNE L0
LDC "public void resources.OnMethodTest#noargs"
INVOKEDYNAMIC $btrace$org$openjdk$btrace$runtime$auxiliary$TraceAllTest$doall(Ljava/lang/String;)V [
// handle kind 0x6 : INVOKESTATIC
org/openjdk/btrace/runtime/Indy.bootstrap(Ljava/lang/invoke/MethodHandles$Lookup;Ljava/lang/String;Ljava/lang/invoke/MethodType;Ljava/lang/String;)Ljava/lang/invoke/CallSite;
// arguments:
"org/openjdk/btrace/runtime/auxiliary/TraceAllTest"
]
FRAME SAME
MAXSTACK = 1
INVOKESTATIC org/openjdk/btrace/runtime/LinkingFlag.get ()I
IFNE L0
LDC "public static void resources.OnMethodTest#noargs$static"
INVOKEDYNAMIC $btrace$org$openjdk$btrace$runtime$auxiliary$TraceAllTest$doall(Ljava/lang/String;)V [
// handle kind 0x6 : INVOKESTATIC
org/openjdk/btrace/runtime/Indy.bootstrap(Ljava/lang/invoke/MethodHandles$Lookup;Ljava/lang/String;Ljava/lang/invoke/MethodType;Ljava/lang/String;)Ljava/lang/invoke/CallSite;
// arguments:
"org/openjdk/btrace/runtime/auxiliary/TraceAllTest"
]
FRAME SAME
MAXSTACK = 1
INVOKESTATIC org/openjdk/btrace/runtime/LinkingFlag.get ()I
IFNE L0
LDC "public long resources.OnMethodTest#args(java.lang.String, long, java.lang.String[], int[])"
INVOKEDYNAMIC $btrace$org$openjdk$btrace$runtime$auxiliary$TraceAllTest$doall(Ljava/lang/String;)V [
// handle kind 0x6 : INVOKESTATIC
org/openjdk/btrace/runtime/Indy.bootstrap(Ljava/lang/invoke/MethodHandles$Lookup;Ljava/lang/String;Ljava/lang/invoke/MethodType;Ljava/lang/String;)Ljava/lang/invoke/CallSite;
// arguments:
"org/openjdk/btrace/runtime/auxiliary/TraceAllTest"
]
FRAME SAME
INVOKESTATIC org/openjdk/btrace/runtime/LinkingFlag.get ()I
IFNE L0
LDC "public static long resources.OnMethodTest#args$static(java.lang.String, long, java.lang.String[], int[])"
INVOKEDYNAMIC $btrace$org$openjdk$btrace$runtime$auxiliary$TraceAllTest$doall(Ljava/lang/String;)V [
// handle kind 0x6 : INVOKESTATIC
org/openjdk/btrace/runtime/Indy.bootstrap(Ljava/lang/invoke/MethodHandles$Lookup;Ljava/lang/String;Ljava/lang/invoke/MethodType;Ljava/lang/String;)Ljava/lang/invoke/CallSite;
// arguments:
"org/openjdk/btrace/runtime/auxiliary/TraceAllTest"
]
FRAME SAME
INVOKESTATIC org/openjdk/btrace/runtime/LinkingFlag.get ()I
IFNE L0
LDC "public static long resources.OnMethodTest#callTopLevelStatic(java.lang.String, long)"
INVOKEDYNAMIC $btrace$org$openjdk$btrace$runtime$auxiliary$TraceAllTest$doall(Ljava/lang/String;)V [
// handle kind 0x6 : INVOKESTATIC
org/openjdk/btrace/runtime/Indy.bootstrap(Ljava/lang/invoke/MethodHandles$Lookup;Ljava/lang/String;Ljava/lang/invoke/MethodType;Ljava/lang/String;)Ljava/lang/invoke/CallSite;
// arguments:
"org/openjdk/btrace/runtime/auxiliary/TraceAllTest"
]
FRAME SAME
INVOKESTATIC org/openjdk/btrace/runtime/LinkingFlag.get ()I
IFNE L0
LDC "public static long resources.OnMethodTest#callTargetStatic(java.lang.String, long)"
INVOKEDYNAMIC $btrace$org$openjdk$btrace$runtime$auxiliary$TraceAllTest$doall(Ljava/lang/String;)V [
// handle kind 0x6 : INVOKESTATIC
org/openjdk/btrace/runtime/Indy.bootstrap(Ljava/lang/invoke/MethodHandles$Lookup;Ljava/lang/String;Ljava/lang/invoke/MethodType;Ljava/lang/String;)Ljava/lang/invoke/CallSite;
// arguments:
"org/openjdk/btrace/runtime/auxiliary/TraceAllTest"
]
FRAME SAME
INVOKESTATIC org/openjdk/btrace/runtime/LinkingFlag.get ()I
IFNE L0
LDC "public long resources.OnMethodTest#callTopLevel(java.lang.String, long)"
INVOKEDYNAMIC $btrace$org$openjdk$btrace$runtime$auxiliary$TraceAllTest$doall(Ljava/lang/String;)V [
// handle kind 0x6 : INVOKESTATIC
org/openjdk/btrace/runtime/Indy.bootstrap(Ljava/lang/invoke/MethodHandles$Lookup;Ljava/lang/String;Ljava/lang/invoke/MethodType;Ljava/lang/String;)Ljava/lang/invoke/CallSite;
// arguments:
"org/openjdk/btrace/runtime/auxiliary/TraceAllTest"
]
FRAME SAME
INVOKESTATIC org/openjdk/btrace/runtime/LinkingFlag.get ()I
IFNE L0
LDC "private long resources.OnMethodTest#callTarget(java.lang.String, long)"
INVOKEDYNAMIC $btrace$org$openjdk$btrace$runtime$auxiliary$TraceAllTest$doall(Ljava/lang/String;)V [
// handle kind 0x6 : INVOKESTATIC
org/openjdk/btrace/runtime/Indy.bootstrap(Ljava/lang/invoke/MethodHandles$Lookup;Ljava/lang/String;Ljava/lang/invoke/MethodType;Ljava/lang/String;)Ljava/lang/invoke/CallSite;
// arguments:
"org/openjdk/btrace/runtime/auxiliary/TraceAllTest"
]
FRAME SAME
INVOKESTATIC org/openjdk/btrace/runtime/LinkingFlag.get ()I
IFNE L0
LDC "public void resources.OnMethodTest#exception"
INVOKEDYNAMIC $btrace$org$openjdk$btrace$runtime$auxiliary$TraceAllTest$doall(Ljava/lang/String;)V [
// handle kind 0x6 : INVOKESTATIC
org/openjdk/btrace/runtime/Indy.bootstrap(Ljava/lang/invoke/MethodHandles$Lookup;Ljava/lang/String;Ljava/lang/invoke/MethodType;Ljava/lang/String;)Ljava/lang/invoke/CallSite;
// arguments:
"org/openjdk/btrace/runtime/auxiliary/TraceAllTest"
]
FRAME SAME
INVOKESTATIC org/openjdk/btrace/runtime/LinkingFlag.get ()I
IFNE L0
LDC "public void resources.OnMethodTest#uncaught"
INVOKEDYNAMIC $btrace$org$openjdk$btrace$runtime$auxiliary$TraceAllTest$doall(Ljava/lang/String;)V [
// handle kind 0x6 : INVOKESTATIC
org/openjdk/btrace/runtime/Indy.bootstrap(Ljava/lang/invoke/MethodHandles$Lookup;Ljava/lang/String;Ljava/lang/invoke/MethodType;Ljava/lang/String;)Ljava/lang/invoke/CallSite;
// arguments:
"org/openjdk/btrace/runtime/auxiliary/TraceAllTest"
]
FRAME SAME
INVOKESTATIC org/openjdk/btrace/runtime/LinkingFlag.get ()I
IFNE L0
LDC "public void resources.OnMethodTest#array(int)"
INVOKEDYNAMIC $btrace$org$openjdk$btrace$runtime$auxiliary$TraceAllTest$doall(Ljava/lang/String;)V [
// handle kind 0x6 : INVOKESTATIC
org/openjdk/btrace/runtime/Indy.bootstrap(Ljava/lang/invoke/MethodHandles$Lookup;Ljava/lang/String;Ljava/lang/invoke/MethodType;Ljava/lang/String;)Ljava/lang/invoke/CallSite;
// arguments:
"org/openjdk/btrace/runtime/auxiliary/TraceAllTest"
]
FRAME SAME
INVOKESTATIC org/openjdk/btrace/runtime/LinkingFlag.get ()I
IFNE L0
LDC "public void resources.OnMethodTest#field"
INVOKEDYNAMIC $btrace$org$openjdk$btrace$runtime$auxiliary$TraceAllTest$doall(Ljava/lang/String;)V [
// handle kind 0x6 : INVOKESTATIC
org/openjdk/btrace/runtime/Indy.bootstrap(Ljava/lang/invoke/MethodHandles$Lookup;Ljava/lang/String;Ljava/lang/invoke/MethodType;Ljava/lang/String;)Ljava/lang/invoke/CallSite;
// arguments:
"org/openjdk/btrace/runtime/auxiliary/TraceAllTest"
]
FRAME SAME
INVOKESTATIC org/openjdk/btrace/runtime/LinkingFlag.get ()I
IFNE L0
LDC "public void resources.OnMethodTest#newObject"
INVOKEDYNAMIC $btrace$org$openjdk$btrace$runtime$auxiliary$TraceAllTest$doall(Ljava/lang/String;)V [
// handle kind 0x6 : INVOKESTATIC
org/openjdk/btrace/runtime/Indy.bootstrap(Ljava/lang/invoke/MethodHandles$Lookup;Ljava/lang/String;Ljava/lang/invoke/MethodType;Ljava/lang/String;)Ljava/lang/invoke/CallSite;
// arguments:
"org/openjdk/btrace/runtime/auxiliary/TraceAllTest"
]
FRAME SAME
INVOKESTATIC org/openjdk/btrace/runtime/LinkingFlag.get ()I
IFNE L0
LDC "public void resources.OnMethodTest#newArray"
INVOKEDYNAMIC $btrace$org$openjdk$btrace$runtime$auxiliary$TraceAllTest$doall(Ljava/lang/String;)V [
// handle kind 0x6 : INVOKESTATIC
org/openjdk/btrace/runtime/Indy.bootstrap(Ljava/lang/invoke/MethodHandles$Lookup;Ljava/lang/String;Ljava/lang/invoke/MethodType;Ljava/lang/String;)Ljava/lang/invoke/CallSite;
// arguments:
"org/openjdk/btrace/runtime/auxiliary/TraceAllTest"
]
FRAME SAME
INVOKESTATIC org/openjdk/btrace/runtime/LinkingFlag.get ()I
IFNE L0
LDC "public void resources.OnMethodTest#casts"
INVOKEDYNAMIC $btrace$org$openjdk$btrace$runtime$auxiliary$TraceAllTest$doall(Ljava/lang/String;)V [
// handle kind 0x6 : INVOKESTATIC
org/openjdk/btrace/runtime/Indy.bootstrap(Ljava/lang/invoke/MethodHandles$Lookup;Ljava/lang/String;Ljava/lang/invoke/MethodType;Ljava/lang/String;)Ljava/lang/invoke/CallSite;
// arguments:
"org/openjdk/btrace/runtime/auxiliary/TraceAllTest"
]
FRAME SAME
INVOKESTATIC org/openjdk/btrace/runtime/LinkingFlag.get ()I
IFNE L4
LDC "public void resources.OnMethodTest#sync"
INVOKEDYNAMIC $btrace$org$openjdk$btrace$runtime$auxiliary$TraceAllTest$doall(Ljava/lang/String;)V [
// handle kind 0x6 : INVOKESTATIC
org/openjdk/btrace/runtime/Indy.bootstrap(Ljava/lang/invoke/MethodHandles$Lookup;Ljava/lang/String;Ljava/lang/invoke/MethodType;Ljava/lang/String;)Ljava/lang/invoke/CallSite;
// arguments:
"org/openjdk/btrace/runtime/auxiliary/TraceAllTest"
]
FRAME SAME
INVOKESTATIC org/openjdk/btrace/runtime/LinkingFlag.get ()I
IFNE L0
LDC "public long resources.OnMethodTest#callTopLevel1(java.lang.String, long)"
INVOKEDYNAMIC $btrace$org$openjdk$btrace$runtime$auxiliary$TraceAllTest$doall(Ljava/lang/String;)V [
// handle kind 0x6 : INVOKESTATIC
org/openjdk/btrace/runtime/Indy.bootstrap(Ljava/lang/invoke/MethodHandles$Lookup;Ljava/lang/String;Ljava/lang/invoke/MethodType;Ljava/lang/String;)Ljava/lang/invoke/CallSite;
// arguments:
"org/openjdk/btrace/runtime/auxiliary/TraceAllTest"
]
FRAME SAME
INVOKESTATIC org/openjdk/btrace/runtime/LinkingFlag.get ()I
IFNE L0
LDC "private long resources.OnMethodTest#calLTargetX(java.lang.String, long)"
INVOKEDYNAMIC $btrace$org$openjdk$btrace$runtime$auxiliary$TraceAllTest$doall(Ljava/lang/String;)V [
// handle kind 0x6 : INVOKESTATIC
org/openjdk/btrace/runtime/Indy.bootstrap(Ljava/lang/invoke/MethodHandles$Lookup;Ljava/lang/String;Ljava/lang/invoke/MethodType;Ljava/lang/String;)Ljava/lang/invoke/CallSite;
// arguments:
"org/openjdk/btrace/runtime/auxiliary/TraceAllTest"
]
FRAME SAME
INVOKESTATIC org/openjdk/btrace/runtime/LinkingFlag.get ()I
IFNE L0
LDC "public long resources.OnMethodTest#argsMultiReturn(java.lang.String, long, java.lang.String[], int[])"
INVOKEDYNAMIC $btrace$org$openjdk$btrace$runtime$auxiliary$TraceAllTest$doall(Ljava/lang/String;)V [
// handle kind 0x6 : INVOKESTATIC
org/openjdk/btrace/runtime/Indy.bootstrap(Ljava/lang/invoke/MethodHandles$Lookup;Ljava/lang/String;Ljava/lang/invoke/MethodType;Ljava/lang/String;)Ljava/lang/invoke/CallSite;
// arguments:
"org/openjdk/btrace/runtime/auxiliary/TraceAllTest"
]
FRAME SAME
INVOKESTATIC org/openjdk/btrace/runtime/LinkingFlag.get ()I
IFNE L0
LDC "public void resources.OnMethodTest#staticField"
INVOKEDYNAMIC $btrace$org$openjdk$btrace$runtime$auxiliary$TraceAllTest$doall(Ljava/lang/String;)V [
// handle kind 0x6 : INVOKESTATIC
org/openjdk/btrace/runtime/Indy.bootstrap(Ljava/lang/invoke/MethodHandles$Lookup;Ljava/lang/String;Ljava/lang/invoke/MethodType;Ljava/lang/String;)Ljava/lang/invoke/CallSite;
// arguments:
"org/openjdk/btrace/runtime/auxiliary/TraceAllTest"
]
FRAME SAME
INVOKESTATIC org/openjdk/btrace/runtime/LinkingFlag.get ()I
IFNE L4
LDC "public void resources.OnMethodTest#syncM"
INVOKEDYNAMIC $btrace$org$openjdk$btrace$runtime$auxiliary$TraceAllTest$doall(Ljava/lang/String;)V [
// handle kind 0x6 : INVOKESTATIC
org/openjdk/btrace/runtime/Indy.bootstrap(Ljava/lang/invoke/MethodHandles$Lookup;Ljava/lang/String;Ljava/lang/invoke/MethodType;Ljava/lang/String;)Ljava/lang/invoke/CallSite;
// arguments:
"org/openjdk/btrace/runtime/auxiliary/TraceAllTest"
]
FRAME SAME
INVOKESTATIC org/openjdk/btrace/runtime/LinkingFlag.get ()I
IFNE L0
LDC "public java.lang.String resources.OnMethodTest#argsTypeMatch(java.util.ArrayList)"
INVOKEDYNAMIC $btrace$org$openjdk$btrace$runtime$auxiliary$TraceAllTest$doall(Ljava/lang/String;)V [
// handle kind 0x6 : INVOKESTATIC
org/openjdk/btrace/runtime/Indy.bootstrap(Ljava/lang/invoke/MethodHandles$Lookup;Ljava/lang/String;Ljava/lang/invoke/MethodType;Ljava/lang/String;)Ljava/lang/invoke/CallSite;
// arguments:
"org/openjdk/btrace/runtime/auxiliary/TraceAllTest"
]
FRAME SAME
INVOKESTATIC org/openjdk/btrace/runtime/LinkingFlag.get ()I
IFNE L0
LDC "public void resources.OnMethodTest#caught"
INVOKEDYNAMIC $btrace$org$openjdk$btrace$runtime$auxiliary$TraceAllTest$doall(Ljava/lang/String;)V [
// handle kind 0x6 : INVOKESTATIC
org/openjdk/btrace/runtime/Indy.bootstrap(Ljava/lang/invoke/MethodHandles$Lookup;Ljava/lang/String;Ljava/lang/invoke/MethodType;Ljava/lang/String;)Ljava/lang/invoke/CallSite;
// arguments:
"org/openjdk/btrace/runtime/auxiliary/TraceAllTest"
]
FRAME SAME