LSTORE 4
ASTORE 6
ASTORE 7
LCONST_0
LSTORE 8
INVOKESTATIC java/lang/System.nanoTime ()J
LSTORE 10
ALOAD 7
ALOAD 6
LLOAD 4
LSTORE 12
ASTORE 14
ASTORE 15
ALOAD 15
ALOAD 14
LLOAD 12
INVOKESTATIC java/lang/System.nanoTime ()J
LLOAD 10
LSUB
LSTORE 8
DUP2
LSTORE 16
LLOAD 16
LLOAD 8
ALOAD 14
LLOAD 12
INVOKESTATIC resources/OnMethodTest.$btrace$org$openjdk$btrace$runtime$auxiliary$MethodCallDuration2$args0 (JJLjava/lang/String;J)V
LCONST_0
LSTORE 8
DUP2
LSTORE 18
LLOAD 18
LLOAD 8
ALOAD 6
LLOAD 4
INVOKESTATIC resources/OnMethodTest.$btrace$org$openjdk$btrace$runtime$auxiliary$MethodCallDuration2$args1 (JJLjava/lang/String;J)V
MAXSTACK = 9
MAXLOCALS = 20