ISTORE 4
DUP2
ISTORE 5
ASTORE 6
ILOAD 4
GETSTATIC org/openjdk/btrace/runtime/auxiliary/ArraySetAfterAny.$btrace$$level : I
ICONST_1
ISUB
DUP
ISTORE 7
IFLT L3
L3
FRAME FULL [resources/OnMethodTest I [I I I I [I I] [[I I I]
ILOAD 7
IFLT L4
INVOKESTATIC org/openjdk/btrace/runtime/LinkingFlag.get ()I
IFNE L4
ALOAD 0
ALOAD 6
ILOAD 5
ILOAD 4
INVOKESTATIC java/lang/Integer.valueOf (I)Ljava/lang/Integer;
INVOKESTATIC resources/OnMethodTest.$btrace$org$openjdk$btrace$runtime$auxiliary$ArraySetAfterAny$args (Ljava/lang/Object;Ljava/lang/Object;ILjava/lang/Object;)V
L4
LINENUMBER 98 L4
FRAME SAME
L5
LOCALVARIABLE this Lresources/OnMethodTest; L0 L5 0
LOCALVARIABLE a I L0 L5 1
LOCALVARIABLE arr [I L1 L5 2
LOCALVARIABLE b I L2 L5 3
MAXSTACK = 5
MAXLOCALS = 8

// access flags 0xA
private static $btrace$org$openjdk$btrace$runtime$auxiliary$ArraySetAfterAny$args(Ljava/lang/Object;Ljava/lang/Object;ILjava/lang/Object;)V
@Lorg/openjdk/btrace/core/annotations/OnMethod;(clazz="/.*\\.OnMethodTest/", method="array", location=@Lorg/openjdk/btrace/core/annotations/Location;(value=Lorg/openjdk/btrace/core/annotations/Kind;.ARRAY_SET, where=Lorg/openjdk/btrace/core/annotations/Where;.AFTER), enableAt=@Lorg/openjdk/btrace/core/annotations/Level;(value=">=1"))
// annotable parameter count: 4 (visible)
@Lorg/openjdk/btrace/core/annotations/Self;() // parameter 0
@Lorg/openjdk/btrace/core/annotations/TargetInstance;() // parameter 1
TRYCATCHBLOCK L0 L1 L1 java/lang/Throwable
GETSTATIC org/openjdk/btrace/runtime/auxiliary/ArraySetAfterAny.runtime : Lorg/openjdk/btrace/runtime/BTraceRuntimeImplBase;
INVOKESTATIC org/openjdk/btrace/runtime/BTraceRuntimeAccess.enter (Lorg/openjdk/btrace/core/BTraceRuntime$Impl;)Z
IFNE L0
RETURN
L0
FRAME SAME
LDC "args"
INVOKESTATIC org/openjdk/btrace/core/BTraceUtils.println (Ljava/lang/Object;)V
GETSTATIC org/openjdk/btrace/runtime/auxiliary/ArraySetAfterAny.runtime : Lorg/openjdk/btrace/runtime/BTraceRuntimeImplBase;
INVOKEVIRTUAL org/openjdk/btrace/runtime/BTraceRuntimeImplBase.leave ()V
RETURN
L1
FRAME SAME1 java/lang/Throwable
GETSTATIC org/openjdk/btrace/runtime/auxiliary/ArraySetAfterAny.runtime : Lorg/openjdk/btrace/runtime/BTraceRuntimeImplBase;
DUP_X1
SWAP
INVOKEVIRTUAL org/openjdk/btrace/runtime/BTraceRuntimeImplBase.handleException (Ljava/lang/Throwable;)V
GETSTATIC org/openjdk/btrace/runtime/auxiliary/ArraySetAfterAny.runtime : Lorg/openjdk/btrace/runtime/BTraceRuntimeImplBase;
INVOKEVIRTUAL org/openjdk/btrace/runtime/BTraceRuntimeImplBase.leave ()V
RETURN
MAXSTACK = 3
MAXLOCALS = 4