GETSTATIC org/openjdk/btrace/runtime/auxiliary/FieldGetAfterStatic.$btrace$$level : I
ICONST_1
ISUB
DUP
ISTORE 1
IFLT L1
L1
FRAME APPEND [I]
ILOAD 1
IFLT L2
DUP2
LSTORE 2
INVOKESTATIC org/openjdk/btrace/runtime/LinkingFlag.get ()I
IFNE L2
ALOAD 0
ACONST_NULL
LDC "static field long resources.OnMethodTest#sField"
LLOAD 2
INVOKESTATIC resources/OnMethodTest.$btrace$org$openjdk$btrace$runtime$auxiliary$FieldGetAfterStatic$args (Ljava/lang/Object;Ljava/lang/Object;Ljava/lang/String;J)V
L2
FRAME FULL [resources/OnMethodTest I J] [J]
L3
LINENUMBER 162 L3
L4
LOCALVARIABLE this Lresources/OnMethodTest; L0 L4 0
MAXSTACK = 7
MAXLOCALS = 4

// access flags 0xA
private static $btrace$org$openjdk$btrace$runtime$auxiliary$FieldGetAfterStatic$args(Ljava/lang/Object;Ljava/lang/Object;Ljava/lang/String;J)V
@Lorg/openjdk/btrace/core/annotations/OnMethod;(clazz="/.*\\.OnMethodTest/", method="staticField", location=@Lorg/openjdk/btrace/core/annotations/Location;(value=Lorg/openjdk/btrace/core/annotations/Kind;.FIELD_GET, clazz="resources.OnMethodTest", field="sField", where=Lorg/openjdk/btrace/core/annotations/Where;.AFTER), enableAt=@Lorg/openjdk/btrace/core/annotations/Level;(value=">=1"))
// annotable parameter count: 4 (visible)
@Lorg/openjdk/btrace/core/annotations/Self;() // parameter 0
@Lorg/openjdk/btrace/core/annotations/TargetInstance;() // parameter 1
@Lorg/openjdk/btrace/core/annotations/TargetMethodOrField;(fqn=true) // parameter 2
@Lorg/openjdk/btrace/core/annotations/Return;() // parameter 3
TRYCATCHBLOCK L0 L1 L1 java/lang/Throwable
GETSTATIC org/openjdk/btrace/runtime/auxiliary/FieldGetAfterStatic.runtime : Lorg/openjdk/btrace/runtime/BTraceRuntimeImplBase;
INVOKESTATIC org/openjdk/btrace/runtime/BTraceRuntimeAccess.enter (Lorg/openjdk/btrace/core/BTraceRuntime$Impl;)Z
IFNE L0
RETURN
L0
FRAME SAME
LDC "args"
INVOKESTATIC org/openjdk/btrace/core/BTraceUtils.println (Ljava/lang/Object;)V
GETSTATIC org/openjdk/btrace/runtime/auxiliary/FieldGetAfterStatic.runtime : Lorg/openjdk/btrace/runtime/BTraceRuntimeImplBase;
INVOKEVIRTUAL org/openjdk/btrace/runtime/BTraceRuntimeImplBase.leave ()V
RETURN
L1
FRAME SAME1 java/lang/Throwable
GETSTATIC org/openjdk/btrace/runtime/auxiliary/FieldGetAfterStatic.runtime : Lorg/openjdk/btrace/runtime/BTraceRuntimeImplBase;
DUP_X1
SWAP
INVOKEVIRTUAL org/openjdk/btrace/runtime/BTraceRuntimeImplBase.handleException (Ljava/lang/Throwable;)V
GETSTATIC org/openjdk/btrace/runtime/auxiliary/FieldGetAfterStatic.runtime : Lorg/openjdk/btrace/runtime/BTraceRuntimeImplBase;
INVOKEVIRTUAL org/openjdk/btrace/runtime/BTraceRuntimeImplBase.leave ()V
RETURN
MAXSTACK = 3
MAXLOCALS = 5